.editorconfig
.zenodo.json
AUTHORS.rst
CONTRIBUTING.rst
HISTORY.rst
LICENSE
Makefile
README.rst
pyproject.toml
tox.ini
EnFROSP.egg-info/PKG-INFO
EnFROSP.egg-info/SOURCES.txt
EnFROSP.egg-info/dependency_links.txt
EnFROSP.egg-info/entry_points.txt
EnFROSP.egg-info/not-zip-safe
EnFROSP.egg-info/requires.txt
EnFROSP.egg-info/top_level.txt
enfrosp/__init__.py
enfrosp/cli.py
enfrosp/version.py
enfrosp/data/Earth_Sun_distances_per_day_edited__1980_2030.csv
enfrosp/data/SSI_TSIS-1__350-2500nm.txt
enfrosp/data/index.dat
enfrosp/data/refrindex.dat
enfrosp/data/ssi_opt_enmap.dat
enfrosp/io/__init__.py
enfrosp/io/reader_enmap.py
enfrosp/retrieval/__init__.py
enfrosp/retrieval/constants.py
enfrosp/retrieval/functions.py
enfrosp/retrieval/retrieval.py