Metadata-Version: 2.4
Name: EnFROSP
Version: 0.2.0
Summary: EnMAP Fast Retrieval Of Snow Properties
Author-email: Daniel Scheffler <daniel.scheffler@gfz.de>, Alexander Kokhanovsky <kokhanov@gfz.de>, Karl Segl <segl@gfz.de>
Maintainer-email: Daniel Scheffler <daniel.scheffler@gfz.de>
License: Apache Software License 2.0
Project-URL: Source code, https://git.gfz-potsdam.de/EnMAP/GFZ_Tools_EnMAP_BOX/enfrosp
Project-URL: Issue Tracker, https://git.gfz-potsdam.de/EnMAP/GFZ_Tools_EnMAP_BOX/enfrosp/-/issues
Project-URL: Documentation, https://enmap.git-pages.gfz-potsdam.de/GFZ_Tools_EnMAP_BOX/enfrosp/doc
Project-URL: Change log, https://git.gfz-potsdam.de/EnMAP/GFZ_Tools_EnMAP_BOX/enfrosp/-/blob/main/HISTORY.rst
Keywords: EnMAP,snow,retrieval,hyperspectral,remote sensing,satellite
Classifier: Development Status :: 2 - Pre-Alpha
Classifier: Intended Audience :: Developers
Classifier: License :: OSI Approved :: GNU General Public License v3 or later (GPLv3+)
Classifier: Natural Language :: English
Classifier: Programming Language :: Python :: 3.8
Classifier: Programming Language :: Python :: 3.9
Classifier: Programming Language :: Python :: 3.10
Classifier: Programming Language :: Python :: 3.11
Requires-Python: >=3.8
License-File: LICENSE
Requires-Dist: gdal
Requires-Dist: geoarray
Requires-Dist: numpy
Requires-Dist: scipy
Provides-Extra: doc
Requires-Dist: sphinx-argparse; extra == "doc"
Requires-Dist: sphinx_rtd_theme; extra == "doc"
Provides-Extra: test
Requires-Dist: pytest; extra == "test"
Requires-Dist: pytest-cov; extra == "test"
Requires-Dist: pytest-reporter-html1; extra == "test"
Requires-Dist: urlchecker; extra == "test"
Requires-Dist: geoarray; extra == "test"
Provides-Extra: lint
Requires-Dist: flake8; extra == "lint"
Requires-Dist: pycodestyle; extra == "lint"
Requires-Dist: pydocstyle; extra == "lint"
Provides-Extra: dev
Requires-Dist: enfrosp[test]; extra == "dev"
Requires-Dist: enfrosp[doc]; extra == "dev"
Requires-Dist: enfrosp[lint]; extra == "dev"
Dynamic: license-file
